gym_examples/__init__.py
gym_examples/envs/__init__.py
gym_examples/envs/wsn_env.py
gym_examples-3.0.907.dist-info/METADATA
gym_examples-3.0.907.dist-info/WHEEL
gym_examples-3.0.907.dist-info/top_level.txt
gym_examples-3.0.907.dist-info/RECORD
