Metadata-Version: 2.1
Name: gym_examples
Version: 3.0.907
Summary: A custom environment for multi-agent reinforcement learning focused on WSN routing.
Home-page: https://github.com/gedji/CODES.git
Author: Georges Djimefo
Author-email: djimefo@gmail.com
Requires-Dist: numpy
Requires-Dist: gym ==0.21.0
Requires-Dist: scipy
Requires-Dist: msgpack-numpy
Requires-Dist: tqdm
Requires-Dist: msgpack
